mianshiya_search_mcp/__init__.py
mianshiya_search_mcp/server.py
mianshiya_search_mcp-0.1.0.dist-info/METADATA
mianshiya_search_mcp-0.1.0.dist-info/WHEEL
mianshiya_search_mcp-0.1.0.dist-info/entry_points.txt
mianshiya_search_mcp-0.1.0.dist-info/RECORD
