Metadata-Version: 2.4
Name: mianshiya-search-mcp
Version: 0.1.0
Summary: 面试鸭题目搜索 MCP 服务器
Project-URL: Homepage, https://github.com/co-pine/mianshiya-search-mcp
Project-URL: Repository, https://github.com/co-pine/mianshiya-search-mcp
Author: pine
License-Expression: MIT
Keywords: interview,mcp,mianshiya,面试题,面试鸭
Classifier: Development Status :: 4 - Beta
Classifier: Intended Audience :: Developers
Classifier: License :: OSI Approved :: MIT License
Classifier: Programming Language :: Python :: 3
Classifier: Programming Language :: Python :: 3.10
Classifier: Programming Language :: Python :: 3.11
Classifier: Programming Language :: Python :: 3.12
Classifier: Programming Language :: Python :: 3.13
Classifier: Topic :: Software Development :: Libraries :: Python Modules
Requires-Python: >=3.10
Requires-Dist: httpx>=0.27.0
Requires-Dist: mcp>=1.0.0
